django_api_orm/__init__.py
django_api_orm/async_base.py
django_api_orm/async_client.py
django_api_orm/base.py
django_api_orm/client.py
django_api_orm/exceptions.py
django_api_orm/py.typed
django_api_orm/typing.py
django_api_orm/utils.py
django_api_orm-0.1.0.dist-info/METADATA
django_api_orm-0.1.0.dist-info/WHEEL
django_api_orm-0.1.0.dist-info/licenses/LICENSE
django_api_orm-0.1.0.dist-info/RECORD
