Metadata-Version: 2.4
Name: django-api-orm
Version: 0.1.0
Summary: Django ORM-like interface for external REST APIs with Pydantic validation and httpx
Project-URL: Homepage, https://github.com/mrb101/django-api-orm
Project-URL: Repository, https://github.com/mrb101/django-api-orm
Project-URL: Bug Tracker, https://github.com/mrb101/django-api-orm/issues
Author-email: "Bassel J. Hamadeh" <hamadeh.bassel@tigerlab.com>
License: MIT
License-File: LICENSE
Keywords: api,async,django,httpx,orm,pydantic,rest
Classifier: Development Status :: 4 - Beta
Classifier: Framework :: Django
Classifier: Intended Audience :: Developers
Classifier: License :: OSI Approved :: MIT License
Classifier: Programming Language :: Python :: 3
Classifier: Programming Language :: Python :: 3.10
Classifier: Programming Language :: Python :: 3.11
Classifier: Programming Language :: Python :: 3.12
Classifier: Topic :: Internet :: WWW/HTTP
Classifier: Topic :: Software Development :: Libraries :: Python Modules
Classifier: Typing :: Typed
Requires-Python: >=3.10
Requires-Dist: httpx>=0.27.0
Requires-Dist: pydantic>=2.0.0
Provides-Extra: async
Requires-Dist: httpx[http2]>=0.27.0; extra == 'async'
Provides-Extra: dev
Requires-Dist: black>=23.0.0; extra == 'dev'
Requires-Dist: email-validator>=2.0.0; extra == 'dev'
Requires-Dist: fastapi>=0.109.0; extra == 'dev'
Requires-Dist: mypy>=1.7.0; extra == 'dev'
Requires-Dist: pytest-asyncio>=0.23.0; extra == 'dev'
Requires-Dist: pytest-cov>=4.1.0; extra == 'dev'
Requires-Dist: pytest-mock>=3.12.0; extra == 'dev'
Requires-Dist: pytest>=7.4.0; extra == 'dev'
Requires-Dist: respx>=0.21.0; extra == 'dev'
Requires-Dist: ruff>=0.1.0; extra == 'dev'
Requires-Dist: uvicorn[standard]>=0.27.0; extra == 'dev'
Provides-Extra: docs
Requires-Dist: furo>=2024.1.0; extra == 'docs'
Requires-Dist: myst-parser>=2.0.0; extra == 'docs'
Requires-Dist: sphinx-copybutton>=0.5.0; extra == 'docs'
Requires-Dist: sphinx>=7.0.0; extra == 'docs'
